hoax/ArgParser.py
hoax/DatabaseLoader.py
hoax/GeneticAlgorithm.py
hoax/GridSearch.py
hoax/JsonParser.py
hoax/Logger.py
hoax/NeuralNetwork.py
hoax/Optimizer.py
hoax/RandomSearch.py
hoax/SimulatedAnnealing.py
hoax/__init__.py
hoax/__main__.py
hoax-1.0.0.dist-info/LICENSE
hoax-1.0.0.dist-info/METADATA
hoax-1.0.0.dist-info/WHEEL
hoax-1.0.0.dist-info/entry_points.txt
hoax-1.0.0.dist-info/top_level.txt
hoax-1.0.0.dist-info/RECORD
