Metadata-Version: 2.1
Name: hoax
Version: 1.0.0
Summary: Hyperparemeter Optimzation Algorithms Explorer
Author-email: Albert Thie <alb0rt@gmail.com>
License: Apache License
Project-URL: Homepage, https://github.com/AlbertThie/HOAX
Keywords: machine learning,quantum chemistry,optimzation
Classifier: License :: OSI Approved :: MIT License
Classifier: Programming Language :: Python
Classifier: Programming Language :: Python :: 3
Requires-Python: >=3.8
License-File: LICENSE
Requires-Dist: torch
Requires-Dist: numpy
Requires-Dist: tomli ; python_version < "3.11"
Provides-Extra: dev
Requires-Dist: black ; extra == 'dev'
Requires-Dist: bumpver ; extra == 'dev'
Requires-Dist: isort ; extra == 'dev'
Requires-Dist: pip-tools ; extra == 'dev'
Requires-Dist: pytest ; extra == 'dev'
